computer/__init__.py
computer/agents/__init__.py
computer/agents/agents.py
computer/ai/__init__.py
computer/ai/ai.py
computer/audio/__init__.py
computer/audio/audio.py
computer/browser/__init__.py
computer/browser/advanced.py
computer/browser/advanced_docker.py
computer/browser/browser.py
computer/browser/old_browser.py
computer/calendar/__init__.py
computer/calendar/calendar.py
computer/calendar/next_calendar.py
computer/cli.py
computer/clipboard/__init__.py
computer/clipboard/clipboard.py
computer/computer.py
computer/contacts/__init__.py
computer/contacts/contacts.py
computer/developer/__init__.py
computer/developer/developer.py
computer/display/__init__.py
computer/display/display.py
computer/display/point/point.py
computer/docs/__init__.py
computer/docs/docs.py
computer/document/__init__.py
computer/document/document.py
computer/document/template.py
computer/document/template_system.py
computer/files/__init__.py
computer/files/files.py
computer/files/read_pdf.py
computer/image/__init__.py
computer/image/image.py
computer/keyboard/__init__.py
computer/keyboard/keyboard.py
computer/keyboard/rich.py
computer/mail/__init__.py
computer/mail/mail.py
computer/mouse/__init__.py
computer/mouse/mouse.py
computer/os/__init__.py
computer/os/os.py
computer/siri/__init__.py
computer/siri/siri.py
computer/skills/skills.py
computer/sms/__init__.py
computer/sms/sms.py
computer/template/__init__.py
computer/template/audio.py
computer/ui/__init__.py
computer/utils/computer_vision.py
computer/utils/get_active_window.py
computer/utils/html_to_png_base64.py
computer/utils/lazy_import.py
computer/utils/recipient_utils.py
computer/utils/run_applescript.py
computer/video/__init__.py
computer/video/video.py
computer/vision/__init__.py
computer/vision/vision.py
languagetools-0.1.17.dist-info/METADATA
languagetools-0.1.17.dist-info/WHEEL
languagetools-0.1.17.dist-info/entry_points.txt
languagetools-0.1.17.dist-info/RECORD
